{"audio_filepath": "voxconverse_test_wav/cawnd.wav", "offset": 0.0, "duration": 49.49, "label": "UNK", "uniq_id": "cawnd"}
{"audio_filepath": "voxconverse_test_wav/cawnd.wav", "offset": 50.44, "duration": 153.77001, "label": "UNK", "uniq_id": "cawnd"}
{"audio_filepath": "voxconverse_test_wav/cawnd.wav", "offset": 205.64, "duration": 69.12999, "label": "UNK", "uniq_id": "cawnd"}
{"audio_filepath": "voxconverse_test_wav/cawnd.wav", "offset": 275.48001, "duration": 7.69, "label": "UNK", "uniq_id": "cawnd"}
{"audio_filepath": "voxconverse_test_wav/cawnd.wav", "offset": 283.79999, "duration": 79.05002, "label": "UNK", "uniq_id": "cawnd"}
{"audio_filepath": "voxconverse_test_wav/cawnd.wav", "offset": 364.60001, "duration": 122.16998, "label": "UNK", "uniq_id": "cawnd"}
{"audio_filepath": "voxconverse_test_wav/cawnd.wav", "offset": 488.60001, "duration": 24.56998, "label": "UNK", "uniq_id": "cawnd"}
{"audio_filepath": "voxconverse_test_wav/cawnd.wav", "offset": 516.20001, "duration": 0.96997, "label": "UNK", "uniq_id": "cawnd"}
{"audio_filepath": "voxconverse_test_wav/cawnd.wav", "offset": 517.88, "duration": 4.81, "label": "UNK", "uniq_id": "cawnd"}
{"audio_filepath": "voxconverse_test_wav/cawnd.wav", "offset": 524.28003, "duration": 28.32983, "label": "UNK", "uniq_id": "cawnd"}
{"audio_filepath": "voxconverse_test_wav/cawnd.wav", "offset": 553.96002, "duration": 46.72998, "label": "UNK", "uniq_id": "cawnd"}
{"audio_filepath": "voxconverse_test_wav/cawnd.wav", "offset": 601.23999, "duration": 7.13, "label": "UNK", "uniq_id": "cawnd"}
{"audio_filepath": "voxconverse_test_wav/cawnd.wav", "offset": 609.47998, "duration": 4.97003, "label": "UNK", "uniq_id": "cawnd"}
{"audio_filepath": "voxconverse_test_wav/cawnd.wav", "offset": 615.0, "duration": 55.77002, "label": "UNK", "uniq_id": "cawnd"}
{"audio_filepath": "voxconverse_test_wav/cawnd.wav", "offset": 671.32001, "duration": 12.01001, "label": "UNK", "uniq_id": "cawnd"}
{"audio_filepath": "voxconverse_test_wav/cawnd.wav", "offset": 683.88, "duration": 11.77002, "label": "UNK", "uniq_id": "cawnd"}
{"audio_filepath": "voxconverse_test_wav/cawnd.wav", "offset": 697.56, "duration": 12.40997, "label": "UNK", "uniq_id": "cawnd"}
{"audio_filepath": "voxconverse_test_wav/cawnd.wav", "offset": 712.12, "duration": 26.41003, "label": "UNK", "uniq_id": "cawnd"}
{"audio_filepath": "voxconverse_test_wav/cawnd.wav", "offset": 739.23999, "duration": 35.21002, "label": "UNK", "uniq_id": "cawnd"}
{"audio_filepath": "voxconverse_test_wav/cawnd.wav", "offset": 775.40002, "duration": 7.37, "label": "UNK", "uniq_id": "cawnd"}
{"audio_filepath": "voxconverse_test_wav/cawnd.wav", "offset": 783.56, "duration": 10.25, "label": "UNK", "uniq_id": "cawnd"}
{"audio_filepath": "voxconverse_test_wav/cawnd.wav", "offset": 795.96002, "duration": 4.81, "label": "UNK", "uniq_id": "cawnd"}
{"audio_filepath": "voxconverse_test_wav/cawnd.wav", "offset": 801.40002, "duration": 14.40997, "label": "UNK", "uniq_id": "cawnd"}
{"audio_filepath": "voxconverse_test_wav/cawnd.wav", "offset": 816.35999, "duration": 50.41003, "label": "UNK", "uniq_id": "cawnd"}
{"audio_filepath": "voxconverse_test_wav/cawnd.wav", "offset": 867.79999, "duration": 2.33002, "label": "UNK", "uniq_id": "cawnd"}
{"audio_filepath": "voxconverse_test_wav/cawnd.wav", "offset": 871.56, "duration": 0.89001, "label": "UNK", "uniq_id": "cawnd"}
{"audio_filepath": "voxconverse_test_wav/cawnd.wav", "offset": 873.0, "duration": 53.13, "label": "UNK", "uniq_id": "cawnd"}
{"audio_filepath": "voxconverse_test_wav/cawnd.wav", "offset": 928.84003, "duration": 24.3299, "label": "UNK", "uniq_id": "cawnd"}
{"audio_filepath": "voxconverse_test_wav/cawnd.wav", "offset": 953.79999, "duration": 8.73004, "label": "UNK", "uniq_id": "cawnd"}
{"audio_filepath": "voxconverse_test_wav/cawnd.wav", "offset": 963.23999, "duration": 77.69006, "label": "UNK", "uniq_id": "cawnd"}
{"audio_filepath": "voxconverse_test_wav/cawnd.wav", "offset": 1043.0, "duration": 15.37, "label": "UNK", "uniq_id": "cawnd"}
{"audio_filepath": "voxconverse_test_wav/cawnd.wav", "offset": 1061.88, "duration": 2.41003, "label": "UNK", "uniq_id": "cawnd"}
{"audio_filepath": "voxconverse_test_wav/cawnd.wav", "offset": 1066.52002, "duration": 9.37, "label": "UNK", "uniq_id": "cawnd"}
{"audio_filepath": "voxconverse_test_wav/cawnd.wav", "offset": 1077.23999, "duration": 41.69006, "label": "UNK", "uniq_id": "cawnd"}
{"audio_filepath": "voxconverse_test_wav/cawnd.wav", "offset": 1120.52002, "duration": 57.77002, "label": "UNK", "uniq_id": "cawnd"}
{"audio_filepath": "voxconverse_test_wav/cawnd.wav", "offset": 1179.88, "duration": 20.184, "label": "UNK", "uniq_id": "cawnd"}
